streamlit_url_fragments/__init__.py
streamlit_url_fragments/build/asset-manifest.json
streamlit_url_fragments/build/index.html
streamlit_url_fragments/build/static/js/2.eb18462b.chunk.js
streamlit_url_fragments/build/static/js/2.eb18462b.chunk.js.LICENSE.txt
streamlit_url_fragments/build/static/js/2.eb18462b.chunk.js.map
streamlit_url_fragments/build/static/js/main.171be1f5.chunk.js
streamlit_url_fragments/build/static/js/main.171be1f5.chunk.js.map
streamlit_url_fragments/build/static/js/runtime-main.6dd7e1ed.js
streamlit_url_fragments/build/static/js/runtime-main.6dd7e1ed.js.map
streamlit_url_fragments/package-lock.json
streamlit_url_fragments/package.json
streamlit_url_fragments/public/index.html
streamlit_url_fragments/src/index.ts
streamlit_url_fragments/src/react-app-env.d.ts
streamlit_url_fragments/tsconfig.json
streamlit_url_fragments-0.1.2.dist-info/METADATA
streamlit_url_fragments-0.1.2.dist-info/WHEEL
streamlit_url_fragments-0.1.2.dist-info/RECORD
