Metadata-Version: 2.1
Name: streamlit-url-fragments
Version: 0.1.2
Summary: Get the URL fragment(s) (part after #) from Streamlit
License: Apache-2.0
Author: Ang Hou Fu
Author-email: houfu@lovelawrobots.com
Requires-Python: >=3.8,<4.0
Classifier: License :: OSI Approved :: Apache Software License
Classifier: Programming Language :: Python :: 3
Classifier: Programming Language :: Python :: 3.8
Classifier: Programming Language :: Python :: 3.9
Classifier: Programming Language :: Python :: 3.10
Classifier: Programming Language :: Python :: 3.11
Classifier: Programming Language :: Python :: 3.12
Requires-Dist: importlib-resources (>=5.4.0,<6.0.0)
Requires-Dist: streamlit (>0.63)
